{
	"configurations" : 
	[
		{
			"directories" : 
			[
				{
					"build" : ".",
					"jsonFile" : "directory-.-Debug-d0094a50bb2071803777.json",
					"minimumCMakeVersion" : 
					{
						"string" : "3.24"
					},
					"projectIndex" : 0,
					"source" : ".",
					"targetIndexes" : 
					[
						0,
						1
					]
				}
			],
			"name" : "Debug",
			"projects" : 
			[
				{
					"directoryIndexes" : 
					[
						0
					],
					"name" : "Controller",
					"targetIndexes" : 
					[
						0,
						1
					]
				}
			],
			"targets" : 
			[
				{
					"directoryIndex" : 0,
					"id" : "Controller::@6890427a1f51a3e7e1df",
					"jsonFile" : "target-Controller-Debug-ae94b75301035c577a74.json",
					"name" : "Controller",
					"projectIndex" : 0
				},
				{
					"directoryIndex" : 0,
					"id" : "Test::@6890427a1f51a3e7e1df",
					"jsonFile" : "target-Test-Debug-9fff2e65c650eb8b39f2.json",
					"name" : "Test",
					"projectIndex" : 0
				}
			]
		}
	],
	"kind" : "codemodel",
	"paths" : 
	{
		"build" : "D:/SELF_project/Controller/cmake-build-debug",
		"source" : "D:/SELF_project/Controller"
	},
	"version" : 
	{
		"major" : 2,
		"minor" : 4
	}
}
